rate_limited/__init__.py
rate_limited/calls.py
rate_limited/exceptions.py
rate_limited/progress_bar.py
rate_limited/queue.py
rate_limited/resource_manager.py
rate_limited/resources.py
rate_limited/runner.py
rate_limited/threading_utils.py
rate_limited/apis/__init__.py
rate_limited/apis/common.py
rate_limited/apis/openai/chat.py
rate_limited-0.4.0.dist-info/WHEEL
rate_limited-0.4.0.dist-info/METADATA
rate_limited-0.4.0.dist-info/RECORD
