Metadata-Version: 2.1
Name: rate_limited
Version: 0.4.0
Summary: Use slow, rate-limited APIs - like those of Large Language Models - as efficiently as possible
Author-email: Tomasz Pietruszka <tomek.pietruszka@gmail.com>
Requires-Python: >=3.8
Classifier: Programming Language :: Python :: 3
Classifier: License :: OSI Approved :: Apache Software License
Classifier: Operating System :: OS Independent
Requires-Dist: black ; extra == "lint"
Requires-Dist: isort ; extra == "lint"
Requires-Dist: flake8 ; extra == "lint"
Requires-Dist: flake8-isort ; extra == "lint"
Requires-Dist: mypy ; extra == "lint"
Requires-Dist: types-requests ; extra == "lint"
Requires-Dist: types-tqdm ; extra == "lint"
Requires-Dist: aiohttp ; extra == "lint"
Requires-Dist: tqdm ; extra == "progress"
Requires-Dist: pytest ; extra == "test"
Requires-Dist: pytest-xdist ; extra == "test"
Requires-Dist: pytest-timeout ; extra == "test"
Requires-Dist: pytest-asyncio ; extra == "test"
Requires-Dist: aiohttp ; extra == "test"
Requires-Dist: requests ; extra == "test"
Project-URL: Bug Tracker, https://github.com/tpietruszka/rate_limited/issues
Project-URL: Homepage, https://github.com/tpietruszka/rate_limited
Provides-Extra: lint
Provides-Extra: progress
Provides-Extra: test
